TestGeneratorPluginLib/__init__.py
TestGeneratorPluginLib/_built_plugin.py
TestGeneratorPluginLib/_config.py
TestGeneratorPluginLib/_firebase.py
TestGeneratorPluginLib/_language.py
TestGeneratorPluginLib/_managers.py
TestGeneratorPluginLib/_plugin.py
TestGeneratorPluginLib/_plugin_setup.py
TestGeneratorPluginLib/_widgets.py
TestGeneratorPluginLib-1.2.6.dist-info/LICENSE
TestGeneratorPluginLib-1.2.6.dist-info/METADATA
TestGeneratorPluginLib-1.2.6.dist-info/WHEEL
TestGeneratorPluginLib-1.2.6.dist-info/top_level.txt
TestGeneratorPluginLib-1.2.6.dist-info/RECORD
