Metadata-Version: 2.1
Name: TestGeneratorPluginLib
Version: 1.2.6
Summary: A TestGeneratorPluginLib package.
Home-page: https://github.com/SergeiKrivko
Author: SergeiKrivko
License: MIT License
Requires-Python: >=3.10
License-File: LICENSE
Requires-Dist: PyQt6
Requires-Dist: qasync
Requires-Dist: PyQtUIkit
Requires-Dist: requests
